django_oauth_hub/__init__.py
django_oauth_hub/fields.py
django_oauth_hub/locale/nl/LC_MESSAGES/django.po
django_oauth_hub/models.py
django_oauth_hub/oauth_client/__init__.py
django_oauth_hub/oauth_client/admin.py
django_oauth_hub/oauth_client/apps.py
django_oauth_hub/oauth_client/backend/__init__.py
django_oauth_hub/oauth_client/backend/base.py
django_oauth_hub/oauth_client/backend/default.py
django_oauth_hub/oauth_client/forms.py
django_oauth_hub/oauth_client/locale/nl/LC_MESSAGES/django.po
django_oauth_hub/oauth_client/migrations/0001_initial.py
django_oauth_hub/oauth_client/migrations/0002_add_oauth_client_is_choice.py
django_oauth_hub/oauth_client/migrations/__init__.py
django_oauth_hub/oauth_client/models/__init__.py
django_oauth_hub/oauth_client/models/oauth_client.py
django_oauth_hub/oauth_client/models/oauth_client_connection.py
django_oauth_hub/oauth_client/models/oauth_client_token.py
django_oauth_hub/oauth_client/providers.py
django_oauth_hub/oauth_client/tasks.py
django_oauth_hub/oauth_client/templates/oauth_client/connect.html
django_oauth_hub/oauth_client/templates/oauth_client/connections.html
django_oauth_hub/oauth_client/templates/oauth_client/disconnect.html
django_oauth_hub/oauth_client/templates/oauth_client/login.html
django_oauth_hub/oauth_client/tests.py
django_oauth_hub/oauth_client/urls.py
django_oauth_hub/oauth_client/views.py
django_oauth_hub/oauth_server/__init__.py
django_oauth_hub/oauth_server/admin.py
django_oauth_hub/oauth_server/apps.py
django_oauth_hub/oauth_server/locale/nl/LC_MESSAGES/django.po
django_oauth_hub/oauth_server/migrations/__init__.py
django_oauth_hub/oauth_server/models.py
django_oauth_hub/oauth_server/tests.py
django_oauth_hub/oauth_server/views.py
django_oauth_hub/settings.py
django_oauth_hub/util.py
django_oauth_hub-0.0.5.dist-info/LICENSE.md
django_oauth_hub-0.0.5.dist-info/WHEEL
django_oauth_hub-0.0.5.dist-info/METADATA
django_oauth_hub-0.0.5.dist-info/RECORD
