Metadata-Version: 2.1
Name: django-oauth-hub
Version: 0.0.5
Summary: OAuth client and server for Django using authlib.
Home-page: https://github.com/DanielHuisman/django-oauth-hub
License: MIT
Keywords: django,oauth,client,server,authlib
Author: Daniel Huisman
Author-email: daniel@huisman.me
Maintainer: Daniel Huisman
Maintainer-email: daniel@huisman.me
Requires-Python: >=3.10,<4.0
Classifier: Development Status :: 2 - Pre-Alpha
Classifier: Environment :: Web Environment
Classifier: Framework :: Django
Classifier: Intended Audience :: Developers
Classifier: License :: OSI Approved :: MIT License
Classifier: Programming Language :: Python
Classifier: Programming Language :: Python :: 3
Classifier: Programming Language :: Python :: 3.10
Classifier: Programming Language :: Python :: 3.11
Classifier: Programming Language :: Python :: 3
Classifier: Topic :: Software Development :: Libraries :: Python Modules
Requires-Dist: Authlib (>=1.1.0,<2.0.0)
Requires-Dist: django (>=4.0,<5.0)
Requires-Dist: requests (>=2.28.1,<3.0.0)
Project-URL: Repository, https://github.com/DanielHuisman/django-oauth-hub
